nornir_csv
