Metadata-Version: 2.1
Name: nornir-csv
Version: 0.3.0
Summary: CSV Inventory for nornir with hosts, groups, defaults and connection options.
Home-page: https://github.com/matman26/nornir_csv
Author: Matheus Augusto da Silva
Author-email: a.matheus26@hotmail.com
License: apache-2.0
Download-URL: https://github.com/matman26/nornir_csv/archive/refs/tags/v0.3.0.tar.gz
Keywords: nornir,csv,inventory,plugin
Platform: UNKNOWN
Classifier: Development Status :: 3 - Alpha
Classifier: Intended Audience :: Developers
Classifier: Topic :: Software Development :: Build Tools
Classifier: License :: OSI Approved :: Apache Software License
Classifier: Programming Language :: Python :: 3
Classifier: Programming Language :: Python :: 3.5
Classifier: Programming Language :: Python :: 3.6
Classifier: Programming Language :: Python :: 3.7
Classifier: Programming Language :: Python :: 3.8
Classifier: Programming Language :: Python :: 3.9
Classifier: Programming Language :: Python :: 3.10
License-File: LICENSE
License-File: NOTICE
